MANIFEST.in
README.rst
setup.py
docs/HISTORY.txt
docs/INSTALL.txt
docs/LICENSE.GPL
docs/LICENSE.txt
experimental/__init__.py
experimental.backportGS.egg-info/PKG-INFO
experimental.backportGS.egg-info/SOURCES.txt
experimental.backportGS.egg-info/dependency_links.txt
experimental.backportGS.egg-info/entry_points.txt
experimental.backportGS.egg-info/namespace_packages.txt
experimental.backportGS.egg-info/not-zip-safe
experimental.backportGS.egg-info/requires.txt
experimental.backportGS.egg-info/top_level.txt
experimental/backportGS/__init__.py
experimental/backportGS/configure.zcml
experimental/backportGS/patches.py