Metadata-Version: 1.0
Name: experimental.backportGS
Version: 0.2.1
Summary: Monkey-patch Plone 3 to make Plone 4 Generic Setup import steps to continue working
Home-page: https://github.com/RedTurtle/experimental.backportGS
Author: RedTurtle Technology
Author-email: sviluppoplone@redturtle.it
License: GPL
Keywords: plone generic-setup backport
Platform: UNKNOWN
Classifier: Framework :: Plone
Classifier: Framework :: Plone :: 3.3
Classifier: Development Status :: 4 - Beta
Classifier: Programming Language :: Python
